{
  "annotations": {
    "list": [
      {
        "builtIn": 1,
        "datasource": {
          "type": "grafana",
          "uid": "-- Grafana --"
        },
        "enable": true,
        "hide": true,
        "iconColor": "rgba(0, 211, 255, 1)",
        "name": "Annotations & Alerts",
        "type": "dashboard"
      }
    ]
  },
  "editable": true,
  "fiscalYearStartMonth": 0,
  "graphTooltip": 0,
  "id": null,
  "links": [],
  "panels": [
    {
      "datasource": {
        "type": "prometheus",
        "uid": "prometheus"
      },
      "fieldConfig": {
        "defaults": {
          "unit": "s"
        },
        "overrides": []
      },
      "gridPos": {
        "h": 8,
        "w": 12,
        "x": 0,
        "y": 0
      },
      "id": 1,
      "options": {
        "legend": {
          "displayMode": "list",
          "placement": "bottom"
        },
        "tooltip": {
          "mode": "multi",
          "sort": "desc"
        }
      },
      "targets": [
        {
          "expr": "histogram_quantile(0.50, rate(rate_limit_duration_seconds_bucket{application=\"fluxguard\"}[1m]))",
          "legendFormat": "{{endpoint}} {{algorithm}} {{result}}",
          "refId": "A"
        }
      ],
      "title": "Decision Latency P50",
      "type": "timeseries"
    },
    {
      "datasource": {
        "type": "prometheus",
        "uid": "prometheus"
      },
      "fieldConfig": {
        "defaults": {
          "unit": "s"
        },
        "overrides": []
      },
      "gridPos": {
        "h": 8,
        "w": 12,
        "x": 12,
        "y": 0
      },
      "id": 2,
      "options": {
        "legend": {
          "displayMode": "list",
          "placement": "bottom"
        },
        "tooltip": {
          "mode": "multi",
          "sort": "desc"
        }
      },
      "targets": [
        {
          "expr": "histogram_quantile(0.95, rate(rate_limit_duration_seconds_bucket{application=\"fluxguard\"}[1m]))",
          "legendFormat": "{{endpoint}} {{algorithm}} {{result}}",
          "refId": "A"
        }
      ],
      "title": "Decision Latency P95",
      "type": "timeseries"
    },
    {
      "datasource": {
        "type": "prometheus",
        "uid": "prometheus"
      },
      "fieldConfig": {
        "defaults": {
          "unit": "s"
        },
        "overrides": []
      },
      "gridPos": {
        "h": 8,
        "w": 12,
        "x": 0,
        "y": 8
      },
      "id": 3,
      "options": {
        "legend": {
          "displayMode": "list",
          "placement": "bottom"
        },
        "tooltip": {
          "mode": "multi",
          "sort": "desc"
        }
      },
      "targets": [
        {
          "expr": "histogram_quantile(0.99, rate(rate_limit_duration_seconds_bucket{application=\"fluxguard\"}[1m]))",
          "legendFormat": "{{endpoint}} {{algorithm}} {{result}}",
          "refId": "A"
        }
      ],
      "title": "Decision Latency P99",
      "type": "timeseries"
    },
    {
      "datasource": {
        "type": "prometheus",
        "uid": "prometheus"
      },
      "fieldConfig": {
        "defaults": {
          "unit": "s"
        },
        "overrides": []
      },
      "gridPos": {
        "h": 8,
        "w": 12,
        "x": 12,
        "y": 8
      },
      "id": 4,
      "options": {
        "legend": {
          "displayMode": "list",
          "placement": "bottom"
        },
        "tooltip": {
          "mode": "multi",
          "sort": "desc"
        }
      },
      "targets": [
        {
          "expr": "histogram_quantile(0.99, rate(redis_script_duration_seconds_bucket{application=\"fluxguard\"}[1m]))",
          "legendFormat": "{{script_name}}",
          "refId": "A"
        }
      ],
      "title": "Redis Script Latency P99",
      "type": "timeseries"
    }
  ],
  "refresh": "10s",
  "schemaVersion": 36,
  "style": "dark",
  "tags": [
    "fluxguard"
  ],
  "templating": {
    "list": []
  },
  "time": {
    "from": "now-15m",
    "to": "now"
  },
  "timepicker": {},
  "timezone": "",
  "title": "FluxGuard Limiter Internals",
  "uid": "fg-internals",
  "version": 1,
  "weekStart": ""
}
